{
    "columns": [
        {"label": "所在单位", "field": "所在单位"},
        {"label": "职工号", "field": "职工号"},
        {"label": "姓名", "field": "姓名"},
        {"label": "性别", "field": "性别"},
        {"label": "出生年月日", "field": "出生年月日"},
        {"label": "身份证号", "field": "身份证号"},
        {"label": "民族", "field": "民族"},
        {"label": "籍贯", "field": "籍贯"},
        {"label": "来校年月", "field": "来校年月"},
        {"label": "参加工作年月", "field": "参加工作年月"},
        {"label": "健康状况", "field": "健康状况"},
        {"label": "外侨情况", "field": "外侨情况"},
        {"label": "婚姻状况", "field": "婚姻状况"},
        {"label": "科室名称", "field": "科室名称"},
        {"label": "政治面貌", "field": "政治面貌"},
        {"label": "最后学历", "field": "最后学历"},
        {"label": "最高学历", "field": "最高学历"},
        {"label": "最后学历毕业学校", "field": "最后学历毕业学校"},
        {"label": "最后学历毕业年月", "field": "最后学历毕业年月"},
        {"label": "现职称", "field": "现职称"},
        {"label": "现专业技术职务级别", "field": "现专业技术职务级别"},
        {"label": "专业技术职务资格评定日期", "field": "专业技术职务资格评定日期"},
        {"label": "聘任职称", "field": "聘任职称"},
        {"label": "聘任职称等级", "field": "聘任职称等级"},
        {"label": "现职级日期", "field": "现职级日期"},
        {"label": "从事专业", "field": "从事专业"},
        {"label": "主要岗位", "field": "主要岗位"},
        {"label": "来源类别", "field": "来源类别"},
        {"label": "编制类别", "field": "编制类别"},
        {"label": "人员类别", "field": "人员类别"},
        {"label": "人员状态", "field": "人员状态"},
        {"label": "党政职务", "field": "党政职务"},
        {"label": "党政职务级别", "field": "党政职务级别"},
        {"label": "身份类别", "field": "身份类别"}
    ]
}